tket_exts/__init__.py
tket_exts/py.typed
tket_exts/data/tket/bool.json
tket_exts/data/tket/debug.json
tket_exts/data/tket/futures.json
tket_exts/data/tket/global_phase.json
tket_exts/data/tket/gpu.json
tket_exts/data/tket/guppy.json
tket_exts/data/tket/modifier.json
tket_exts/data/tket/qsystem.json
tket_exts/data/tket/quantum.json
tket_exts/data/tket/result.json
tket_exts/data/tket/rotation.json
tket_exts/data/tket/wasm.json
tket_exts/data/tket/qsystem/random.json
tket_exts/data/tket/qsystem/utils.json
tket_exts/tket/__init__.py
tket_exts/tket/_util.py
tket_exts/tket/bool.py
tket_exts/tket/debug.py
tket_exts/tket/futures.py
tket_exts/tket/global_phase.py
tket_exts/tket/gpu.py
tket_exts/tket/guppy.py
tket_exts/tket/modifier.py
tket_exts/tket/quantum.py
tket_exts/tket/result.py
tket_exts/tket/rotation.py
tket_exts/tket/wasm.py
tket_exts/tket/qsystem/__init__.py
tket_exts/tket/qsystem/random.py
tket_exts/tket/qsystem/utils.py
tket_exts-0.12.0.dist-info/METADATA
tket_exts-0.12.0.dist-info/WHEEL
tket_exts-0.12.0.dist-info/licenses/LICENCE
tket_exts-0.12.0.dist-info/RECORD
